s2i2a/__init__.py
s2i2a/main.py
s2i2a/test_s2i2a.py
s2i2a-0.0.9.dist-info/LICENSE
s2i2a-0.0.9.dist-info/METADATA
s2i2a-0.0.9.dist-info/WHEEL
s2i2a-0.0.9.dist-info/entry_points.txt
s2i2a-0.0.9.dist-info/top_level.txt
s2i2a-0.0.9.dist-info/RECORD
