Metadata-Version: 2.1
Name: s2i2a
Version: 0.0.9
Summary: Sweep to int to arguments. Map parameter sweeps to ints to program arguments. Specifically useful for compute canada.
Home-page: https://github.com/Velythyl/s2i2a
Author: Charlie Gauthier
Author-email: charlie.gauthier@umontreal.ca
License: MIT
Platform: UNKNOWN
License-File: LICENSE
